  0           0 RESUME                   0

  1           2 LOAD_CONST               0 (0)
              4 LOAD_CONST               1 (None)
              6 IMPORT_NAME              0 (os)
              8 STORE_NAME               0 (os)

  2          10 LOAD_CONST               0 (0)
             12 LOAD_CONST               1 (None)
             14 IMPORT_NAME              1 (secrets)
             16 STORE_NAME               1 (secrets)

  3          18 LOAD_CONST               0 (0)
             20 LOAD_CONST               2 (('*',))
             22 IMPORT_NAME              2 (base64)
             24 IMPORT_STAR

  7          26 LOAD_CONST               3 (<code object promptGen at 0xd939d0, file "passwordProtector.py", line 7>)
             28 MAKE_FUNCTION            0
             30 STORE_NAME               3 (promptGen)

 30          32 LOAD_CONST               4 (<code object main at 0x7fcd54732230, file "passwordProtector.py", line 30>)
             34 MAKE_FUNCTION            0
             36 STORE_NAME               4 (main)

 33          38 LOAD_NAME                5 (__name__)
             40 LOAD_CONST               5 ('__main__')
             42 COMPARE_OP               2 (==)
             48 POP_JUMP_FORWARD_IF_FALSE    12 (to 74)

 34          50 PUSH_NULL
             52 LOAD_NAME                4 (main)
             54 PRECALL                  0
             58 CALL                     0
             68 POP_TOP
             70 LOAD_CONST               1 (None)
             72 RETURN_VALUE

 33     >>   74 LOAD_CONST               1 (None)
             76 RETURN_VALUE

Disassembly of <code object promptGen at 0xd939d0, file "passwordProtector.py", line 7>:
  7           0 RESUME                   0

  8           2 LOAD_CONST               1 (<code object <lambda> at 0x7fcd54731a30, file "passwordProtector.py", line 8>)
              4 MAKE_FUNCTION            0
              6 STORE_FAST               0 (flipFlops)

 10           8 LOAD_GLOBAL              1 (NULL + open)
             20 LOAD_CONST               2 ('topsneaky.txt')
             22 LOAD_CONST               3 ('rb')
             24 PRECALL                  2
             28 CALL                     2
             38 BEFORE_WITH
             40 STORE_FAST               1 (f)

 11          42 LOAD_FAST                1 (f)
             44 LOAD_METHOD              1 (read)
             66 PRECALL                  0
             70 CALL                     0
             80 STORE_FAST               2 (first)

 10          82 LOAD_CONST               0 (None)
             84 LOAD_CONST               0 (None)
             86 LOAD_CONST               0 (None)
             88 PRECALL                  2
             92 CALL                     2
            102 POP_TOP
            104 JUMP_FORWARD            11 (to 128)
        >>  106 PUSH_EXC_INFO
            108 WITH_EXCEPT_START
            110 POP_JUMP_FORWARD_IF_TRUE     4 (to 120)
            112 RERAISE                  2
        >>  114 COPY                     3
            116 POP_EXCEPT
            118 RERAISE                  1
        >>  120 POP_TOP
            122 POP_EXCEPT
            124 POP_TOP
            126 POP_TOP

 13     >>  128 LOAD_GLOBAL              5 (NULL + secrets)
            140 LOAD_ATTR                3 (token_bytes)
            150 LOAD_GLOBAL              9 (NULL + len)
            162 LOAD_FAST                2 (first)
            164 PRECALL                  1
            168 CALL                     1
            178 PRECALL                  1
            182 CALL                     1
            192 STORE_FAST               3 (bittys)

 15         194 LOAD_GLOBAL             10 (int)
            206 LOAD_METHOD              6 (from_bytes)
            228 LOAD_FAST                2 (first)
            230 PRECALL                  1
            234 CALL                     1
            244 LOAD_GLOBAL             10 (int)
            256 LOAD_METHOD              6 (from_bytes)
            278 LOAD_FAST                3 (bittys)
            280 PRECALL                  1
            284 CALL                     1
            294 BINARY_OP               12 (^)
            298 STORE_FAST               4 (onePointFive)

 16         300 LOAD_FAST                4 (onePointFive)
            302 LOAD_METHOD              7 (to_bytes)
            324 LOAD_GLOBAL              9 (NULL + len)
            336 LOAD_FAST                2 (first)
            338 PRECALL                  1
            342 CALL                     1
            352 PRECALL                  1
            356 CALL                     1
            366 STORE_FAST               5 (second)

 18         368 LOAD_GLOBAL             17 (NULL + b64encode)
            380 LOAD_FAST                5 (second)
            382 PRECALL                  1
            386 CALL                     1
            396 LOAD_METHOD              9 (decode)
            418 LOAD_CONST               4 ('utf-8')
            420 PRECALL                  1
            424 CALL                     1
            434 STORE_FAST               6 (third)

 19         436 LOAD_GLOBAL             17 (NULL + b64encode)
            448 LOAD_FAST                3 (bittys)
            450 PRECALL                  1
            454 CALL                     1
            464 LOAD_METHOD              9 (decode)
            486 LOAD_CONST               4 ('utf-8')
            488 PRECALL                  1
            492 CALL                     1
            502 STORE_FAST               7 (bittysEnc)

 21         504 LOAD_CONST               5 ('')
            506 STORE_FAST               8 (fourth)

 22         508 LOAD_FAST                6 (third)
            510 GET_ITER
        >>  512 FOR_ITER                16 (to 546)
            514 STORE_FAST               9 (each)

 23         516 LOAD_FAST                8 (fourth)
            518 PUSH_NULL
            520 LOAD_FAST                0 (flipFlops)
            522 LOAD_FAST                9 (each)
            524 PRECALL                  1
            528 CALL                     1
            538 BINARY_OP               13 (+=)
            542 STORE_FAST               8 (fourth)
            544 JUMP_BACKWARD           17 (to 512)

 26     >>  546 LOAD_CONST               6 ('Mwahahaha you will n')
            548 LOAD_FAST                8 (fourth)
            550 LOAD_CONST               7 (0)
            552 LOAD_CONST               8 (10)
            554 BUILD_SLICE              2
            556 BINARY_SUBSCR
            566 FORMAT_VALUE             0
            568 LOAD_CONST               9 ('ever crack into my pass')
            570 LOAD_FAST                8 (fourth)
            572 LOAD_CONST               8 (10)
            574 LOAD_CONST               0 (None)
            576 BUILD_SLICE              2
            578 BINARY_SUBSCR
            588 FORMAT_VALUE             0
            590 LOAD_CONST              10 ("word, i'll even give you the key and the executable:::: ")
            592 LOAD_FAST                7 (bittysEnc)
            594 FORMAT_VALUE             0
            596 BUILD_STRING             6
            598 STORE_FAST              10 (fifth)

 28         600 LOAD_FAST               10 (fifth)
            602 RETURN_VALUE
ExceptionTable:
  40 to 80 -> 106 [1] lasti
  106 to 112 -> 114 [3] lasti
  120 to 120 -> 114 [3] lasti

Disassembly of <code object <lambda> at 0x7fcd54731a30, file "passwordProtector.py", line 8>:
  8           0 RESUME                   0
              2 LOAD_GLOBAL              1 (NULL + chr)
             14 LOAD_GLOBAL              3 (NULL + ord)
             26 LOAD_FAST                0 (x)
             28 PRECALL                  1
             32 CALL                     1
             42 LOAD_CONST               1 (1)
             44 BINARY_OP                0 (+)
             48 PRECALL                  1
             52 CALL                     1
             62 RETURN_VALUE

Disassembly of <code object main at 0x7fcd54732230, file "passwordProtector.py", line 30>:
 30           0 RESUME                   0

 31           2 LOAD_GLOBAL              1 (NULL + print)
             14 LOAD_GLOBAL              3 (NULL + promptGen)
             26 PRECALL                  0
             30 CALL                     0
             40 PRECALL                  1
             44 CALL                     1
             54 POP_TOP
             56 LOAD_CONST               0 (None)
             58 RETURN_VALUE
